metahopt/__about__.py
metahopt/__init__.py
metahopt/examples.py
metahopt/local_search.py
metahopt/numeric_search.py
metahopt/scoring.py
metahopt/typing.py
metahopt/utils.py
metahopt-1.1.1.dist-info/METADATA
metahopt-1.1.1.dist-info/WHEEL
metahopt-1.1.1.dist-info/licenses/LICENSE
metahopt-1.1.1.dist-info/RECORD
